<?xml version="1.0"?>
<block>
  <name>Stream Demux</name>
  <key>mysvl_stream_demux</key>
  <category>[mysvl]</category>
  <import>import mysvl</import>
  <make>mysvl.stream_demux($type.size*$vlen, $lengths)</make>
  <param>
    <name>IO Type</name>
    <key>type</key>
    <type>enum</type>
       <option>
          <name>Complex</name>
          <key>complex</key>
          <opt>size:gr.sizeof_gr_complex</opt>
        </option>
        <option>
          <name>Float</name>
          <key>float</key>
          <opt>size:gr.sizeof_float</opt>
        </option>
        <option>
          <name>Int</name>
          <key>int</key>
          <opt>size:gr.sizeof_int</opt>
        </option>
        <option>
          <name>Short</name>
          <key>short</key>
          <opt>size:gr.sizeof_short</opt>
        </option>
        <option>
          <name>Byte</name>
          <key>byte</key>
          <opt>size:gr.sizeof_char</opt>
	    </option>
	</param>
	<param>
		<name>Lengths</name>
		<key>lengths</key>
		<value>1, 1</value>
		<type>int_vector</type>
	</param>
	<param>
        <name>Number of Outputs </name>
        <key>number_outputs</key>
        <value>2</value>
        <type>int</type>
    </param>
	<param>
		<name>Vec Length</name>
		<key>vlen</key>
		<value>1</value>
		<type>int</type>
	</param>
    <check>$number_outputs &gt; 0</check>
	<check>$number_outputs == len($lengths)</check>
	<check>$vlen &gt; 0</check>
	<sink>
		<name>in</name>
		<type>$type</type>
		<vlen>$vlen</vlen>
	</sink>
	<source>
		<name>out</name>
		<type>$type</type>
		<vlen>$vlen</vlen>
		<nports>$number_outputs</nports>
	</source>
</block>
